<collection xmlns="http://exist.sourceforge.net/NS/exist" name="/db/apps/ehri-online-editions/data/early_testimonies" version="1" owner="ehri" group="tei" mode="755" created="2023-07-31T15:44:48.745+02:00">
    <acl entries="0" version="1"/>
    <resource type="XMLResource" name="EHRI-ET-DEGOB0701_HU_EN.xml" skip="no" owner="ehri" group="tei" mode="644" created="2024-10-15T11:28:12.708+02:00" modified="2024-10-15T11:28:12.708+02:00" filename="EHRI-ET-DEGOB0701_HU_EN.xml" mimetype="application/xml">
        <acl entries="0" version="1"/>
    </resource>
    <resource type="XMLResource" name="EHRI-ET-DEGOB0748_HU_EN.xml" skip="no" owner="ehri" group="tei" mode="644" created="2024-10-15T11:28:12.786+02:00" modified="2024-10-15T11:28:12.786+02:00" filename="EHRI-ET-DEGOB0748_HU_EN.xml" mimetype="application/xml">
        <acl entries="0" version="1"/>
    </resource>
    <resource type="XMLResource" name="EHRI-ET-DEGOB0884_HU_EN.xml" skip="no" owner="ehri" group="tei" mode="644" created="2024-10-15T11:28:12.842+02:00" modified="2024-10-15T11:28:12.842+02:00" filename="EHRI-ET-DEGOB0884_HU_EN.xml" mimetype="application/xml">
        <acl entries="0" version="1"/>
    </resource>
    <resource type="XMLResource" name="EHRI-ET-DEGOB1178_HU_EN.xml" skip="no" owner="ehri" group="tei" mode="644" created="2024-10-15T11:28:12.893+02:00" modified="2024-10-15T11:28:12.893+02:00" filename="EHRI-ET-DEGOB1178_HU_EN.xml" mimetype="application/xml">
        <acl entries="0" version="1"/>
    </resource>
    <resource type="XMLResource" name="EHRI-ET-DEGOB1359_HU_EN.xml" skip="no" owner="ehri" group="tei" mode="644" created="2024-10-15T11:28:12.951+02:00" modified="2024-10-15T11:28:12.951+02:00" filename="EHRI-ET-DEGOB1359_HU_EN.xml" mimetype="application/xml">
        <acl entries="0" version="1"/>
    </resource>
    <resource type="XMLResource" name="EHRI-ET-DEGOB1459_HU_EN.xml" skip="no" owner="ehri" group="tei" mode="644" created="2024-10-15T11:28:13.011+02:00" modified="2024-10-15T11:28:13.011+02:00" filename="EHRI-ET-DEGOB1459_HU_EN.xml" mimetype="application/xml">
        <acl entries="0" version="1"/>
    </resource>
    <resource type="XMLResource" name="EHRI-ET-DEGOB1640_HU_EN.xml" skip="no" owner="ehri" group="tei" mode="644" created="2024-10-15T11:28:13.076+02:00" modified="2024-10-15T11:28:13.076+02:00" filename="EHRI-ET-DEGOB1640_HU_EN.xml" mimetype="application/xml">
        <acl entries="0" version="1"/>
    </resource>
    <resource type="XMLResource" name="EHRI-ET-DEGOB2719_HU_EN.xml" skip="no" owner="ehri" group="tei" mode="644" created="2024-10-15T11:28:13.13+02:00" modified="2024-10-15T11:28:13.13+02:00" filename="EHRI-ET-DEGOB2719_HU_EN.xml" mimetype="application/xml">
        <acl entries="0" version="1"/>
    </resource>
    <resource type="XMLResource" name="EHRI-ET-DEGOB2830_HU_EN.xml" skip="no" owner="ehri" group="tei" mode="644" created="2024-10-15T11:28:13.181+02:00" modified="2024-10-15T11:28:13.181+02:00" filename="EHRI-ET-DEGOB2830_HU_EN.xml" mimetype="application/xml">
        <acl entries="0" version="1"/>
    </resource>
    <resource type="XMLResource" name="EHRI-ET-DEGOB3538_HU_EN.xml" skip="no" owner="ehri" group="tei" mode="644" created="2024-10-15T11:28:13.253+02:00" modified="2024-10-15T11:28:13.253+02:00" filename="EHRI-ET-DEGOB3538_HU_EN.xml" mimetype="application/xml">
        <acl entries="0" version="1"/>
    </resource>
    <resource type="XMLResource" name="EHRI-ET-DEGOB3615_HU_EN.xml" skip="no" owner="ehri" group="tei" mode="644" created="2024-10-15T11:28:13.313+02:00" modified="2024-10-15T11:28:13.313+02:00" filename="EHRI-ET-DEGOB3615_HU_EN.xml" mimetype="application/xml">
        <acl entries="0" version="1"/>
    </resource>
    <resource type="XMLResource" name="EHRI-ET-DEGOB3622_HU_EN.xml" skip="no" owner="ehri" group="tei" mode="644" created="2024-10-15T11:28:13.413+02:00" modified="2024-10-15T11:28:13.413+02:00" filename="EHRI-ET-DEGOB3622_HU_EN.xml" mimetype="application/xml">
        <acl entries="0" version="1"/>
    </resource>
    <resource type="XMLResource" name="EHRI-ET-DEGOB3624_HU_EN.xml" skip="no" owner="ehri" group="tei" mode="644" created="2024-10-15T11:28:13.465+02:00" modified="2024-10-15T11:28:13.465+02:00" filename="EHRI-ET-DEGOB3624_HU_EN.xml" mimetype="application/xml">
        <acl entries="0" version="1"/>
    </resource>
    <resource type="XMLResource" name="EHRI-ET-DEGOB3648_HU_EN.xml" skip="no" owner="ehri" group="tei" mode="644" created="2024-10-15T11:28:13.548+02:00" modified="2024-10-15T11:28:13.548+02:00" filename="EHRI-ET-DEGOB3648_HU_EN.xml" mimetype="application/xml">
        <acl entries="0" version="1"/>
    </resource>
    <resource type="XMLResource" name="EHRI-ET-JMP001_CS_EN.xml" skip="no" owner="ehri" group="tei" mode="644" created="2024-10-15T11:28:13.62+02:00" modified="2024-10-15T11:28:13.62+02:00" filename="EHRI-ET-JMP001_CS_EN.xml" mimetype="application/xml">
        <acl entries="0" version="1"/>
    </resource>
    <resource type="XMLResource" name="EHRI-ET-JMP002_CS_EN.xml" skip="no" owner="ehri" group="tei" mode="644" created="2024-10-15T11:28:13.696+02:00" modified="2024-10-15T11:28:13.696+02:00" filename="EHRI-ET-JMP002_CS_EN.xml" mimetype="application/xml">
        <acl entries="0" version="1"/>
    </resource>
    <resource type="XMLResource" name="EHRI-ET-JMP003_CS_EN.xml" skip="no" owner="ehri" group="tei" mode="644" created="2024-10-15T11:28:13.767+02:00" modified="2024-10-15T11:28:13.767+02:00" filename="EHRI-ET-JMP003_CS_EN.xml" mimetype="application/xml">
        <acl entries="0" version="1"/>
    </resource>
    <resource type="XMLResource" name="EHRI-ET-JMP004_CS_EN.xml" skip="no" owner="ehri" group="tei" mode="644" created="2024-10-15T11:28:13.82+02:00" modified="2024-10-15T11:28:13.82+02:00" filename="EHRI-ET-JMP004_CS_EN.xml" mimetype="application/xml">
        <acl entries="0" version="1"/>
    </resource>
    <resource type="XMLResource" name="EHRI-ET-JMP005_CS_EN.xml" skip="no" owner="ehri" group="tei" mode="644" created="2024-10-15T11:28:13.867+02:00" modified="2024-10-15T11:28:13.867+02:00" filename="EHRI-ET-JMP005_CS_EN.xml" mimetype="application/xml">
        <acl entries="0" version="1"/>
    </resource>
    <resource type="XMLResource" name="EHRI-ET-JMP006_CS_EN.xml" skip="no" owner="ehri" group="tei" mode="644" created="2024-10-15T11:28:13.928+02:00" modified="2024-10-15T11:28:13.928+02:00" filename="EHRI-ET-JMP006_CS_EN.xml" mimetype="application/xml">
        <acl entries="0" version="1"/>
    </resource>
    <resource type="XMLResource" name="EHRI-ET-JMP007_CS_EN.xml" skip="no" owner="ehri" group="tei" mode="644" created="2024-10-15T11:28:13.984+02:00" modified="2024-10-15T11:28:13.984+02:00" filename="EHRI-ET-JMP007_CS_EN.xml" mimetype="application/xml">
        <acl entries="0" version="1"/>
    </resource>
    <resource type="XMLResource" name="EHRI-ET-JMP008_CS_EN.xml" skip="no" owner="ehri" group="tei" mode="644" created="2024-10-15T11:28:14.043+02:00" modified="2024-10-15T11:28:14.043+02:00" filename="EHRI-ET-JMP008_CS_EN.xml" mimetype="application/xml">
        <acl entries="0" version="1"/>
    </resource>
    <resource type="XMLResource" name="EHRI-ET-JMP009_CS_EN.xml" skip="no" owner="ehri" group="tei" mode="644" created="2024-10-15T11:28:14.126+02:00" modified="2024-10-15T11:28:14.126+02:00" filename="EHRI-ET-JMP009_CS_EN.xml" mimetype="application/xml">
        <acl entries="0" version="1"/>
    </resource>
    <resource type="XMLResource" name="EHRI-ET-JMP010_CS_EN.xml" skip="no" owner="ehri" group="tei" mode="644" created="2024-10-15T11:28:14.184+02:00" modified="2024-10-15T11:28:14.184+02:00" filename="EHRI-ET-JMP010_CS_EN.xml" mimetype="application/xml">
        <acl entries="0" version="1"/>
    </resource>
    <resource type="XMLResource" name="EHRI-ET-JMP011_CS_EN.xml" skip="no" owner="ehri" group="tei" mode="644" created="2024-10-15T11:28:14.349+02:00" modified="2024-10-15T11:28:14.349+02:00" filename="EHRI-ET-JMP011_CS_EN.xml" mimetype="application/xml">
        <acl entries="0" version="1"/>
    </resource>
    <resource type="XMLResource" name="EHRI-ET-JMP012_CS_EN.xml" skip="no" owner="ehri" group="tei" mode="644" created="2024-10-15T11:28:14.429+02:00" modified="2024-10-15T11:28:14.429+02:00" filename="EHRI-ET-JMP012_CS_EN.xml" mimetype="application/xml">
        <acl entries="0" version="1"/>
    </resource>
    <resource type="XMLResource" name="EHRI-ET-JMP013_CS_EN.xml" skip="no" owner="ehri" group="tei" mode="644" created="2024-10-15T11:28:14.509+02:00" modified="2024-10-15T11:28:14.509+02:00" filename="EHRI-ET-JMP013_CS_EN.xml" mimetype="application/xml">
        <acl entries="0" version="1"/>
    </resource>
    <resource type="XMLResource" name="EHRI-ET-JMP014_CS_EN.xml" skip="no" owner="ehri" group="tei" mode="644" created="2024-10-15T11:28:14.572+02:00" modified="2024-10-15T11:28:14.572+02:00" filename="EHRI-ET-JMP014_CS_EN.xml" mimetype="application/xml">
        <acl entries="0" version="1"/>
    </resource>
    <resource type="XMLResource" name="EHRI-ET-JMP015_CS_EN.xml" skip="no" owner="ehri" group="tei" mode="644" created="2024-10-15T11:28:14.624+02:00" modified="2024-10-15T11:28:14.623+02:00" filename="EHRI-ET-JMP015_CS_EN.xml" mimetype="application/xml">
        <acl entries="0" version="1"/>
    </resource>
    <resource type="XMLResource" name="EHRI-ET-JMP016_DE_EN.xml" skip="no" owner="ehri" group="tei" mode="644" created="2024-10-15T11:28:14.688+02:00" modified="2024-10-15T11:28:14.688+02:00" filename="EHRI-ET-JMP016_DE_EN.xml" mimetype="application/xml">
        <acl entries="0" version="1"/>
    </resource>
    <resource type="XMLResource" name="EHRI-ET-JMP017_DE_EN.xml" skip="no" owner="ehri" group="tei" mode="644" created="2024-10-15T11:28:14.763+02:00" modified="2024-10-15T11:28:14.763+02:00" filename="EHRI-ET-JMP017_DE_EN.xml" mimetype="application/xml">
        <acl entries="0" version="1"/>
    </resource>
    <resource type="XMLResource" name="EHRI-ET-JMP018_DE_EN.xml" skip="no" owner="ehri" group="tei" mode="644" created="2024-10-15T11:28:14.853+02:00" modified="2024-10-15T11:28:14.853+02:00" filename="EHRI-ET-JMP018_DE_EN.xml" mimetype="application/xml">
        <acl entries="0" version="1"/>
    </resource>
    <resource type="XMLResource" name="EHRI-ET-JMP019_DE_EN.xml" skip="no" owner="ehri" group="tei" mode="644" created="2024-10-15T11:28:14.944+02:00" modified="2024-10-15T11:28:14.944+02:00" filename="EHRI-ET-JMP019_DE_EN.xml" mimetype="application/xml">
        <acl entries="0" version="1"/>
    </resource>
    <resource type="XMLResource" name="EHRI-ET-JMP020_DE_EN.xml" skip="no" owner="ehri" group="tei" mode="644" created="2024-10-15T11:28:15.068+02:00" modified="2024-10-15T11:28:15.068+02:00" filename="EHRI-ET-JMP020_DE_EN.xml" mimetype="application/xml">
        <acl entries="0" version="1"/>
    </resource>
    <resource type="XMLResource" name="EHRI-ET-SOV001_YI_EN.xml" skip="no" owner="ehri" group="tei" mode="644" created="2024-10-15T11:28:15.124+02:00" modified="2024-10-15T11:28:15.124+02:00" filename="EHRI-ET-SOV001_YI_EN.xml" mimetype="application/xml">
        <acl entries="0" version="1"/>
    </resource>
    <resource type="XMLResource" name="EHRI-ET-SOV002_YI_EN.xml" skip="no" owner="ehri" group="tei" mode="644" created="2024-10-15T11:28:15.218+02:00" modified="2024-10-15T11:28:15.218+02:00" filename="EHRI-ET-SOV002_YI_EN.xml" mimetype="application/xml">
        <acl entries="0" version="1"/>
    </resource>
    <resource type="XMLResource" name="EHRI-ET-SOV003_YI_EN.xml" skip="no" owner="ehri" group="tei" mode="644" created="2024-10-15T11:28:15.297+02:00" modified="2024-10-15T11:28:15.297+02:00" filename="EHRI-ET-SOV003_YI_EN.xml" mimetype="application/xml">
        <acl entries="0" version="1"/>
    </resource>
    <resource type="XMLResource" name="EHRI-ET-SOV004_YI_EN.xml" skip="no" owner="ehri" group="tei" mode="644" created="2024-10-15T11:28:15.362+02:00" modified="2024-10-15T11:28:15.361+02:00" filename="EHRI-ET-SOV004_YI_EN.xml" mimetype="application/xml">
        <acl entries="0" version="1"/>
    </resource>
    <resource type="XMLResource" name="EHRI-ET-SOV005_YI_EN.xml" skip="no" owner="ehri" group="tei" mode="644" created="2024-10-15T11:28:15.449+02:00" modified="2024-10-15T11:28:15.449+02:00" filename="EHRI-ET-SOV005_YI_EN.xml" mimetype="application/xml">
        <acl entries="0" version="1"/>
    </resource>
    <resource type="XMLResource" name="EHRI-ET-SOV006_YI_EN.xml" skip="no" owner="ehri" group="tei" mode="644" created="2024-10-15T11:28:15.548+02:00" modified="2024-10-15T11:28:15.548+02:00" filename="EHRI-ET-SOV006_YI_EN.xml" mimetype="application/xml">
        <acl entries="0" version="1"/>
    </resource>
    <resource type="XMLResource" name="EHRI-ET-WL1375B189_DE_EN.xml" skip="no" owner="ehri" group="tei" mode="644" created="2024-10-15T11:28:15.625+02:00" modified="2024-10-15T11:28:15.625+02:00" filename="EHRI-ET-WL1375B189_DE_EN.xml" mimetype="application/xml">
        <acl entries="0" version="1"/>
    </resource>
    <resource type="XMLResource" name="EHRI-ET-WL1375B226_NL_EN.xml" skip="no" owner="ehri" group="tei" mode="644" created="2024-10-15T11:28:15.709+02:00" modified="2024-10-15T11:28:15.709+02:00" filename="EHRI-ET-WL1375B226_NL_EN.xml" mimetype="application/xml">
        <acl entries="0" version="1"/>
    </resource>
    <resource type="XMLResource" name="EHRI-ET-WL1375B307_DE_EN.xml" skip="no" owner="ehri" group="tei" mode="644" created="2024-10-15T11:28:15.782+02:00" modified="2024-10-15T11:28:15.782+02:00" filename="EHRI-ET-WL1375B307_DE_EN.xml" mimetype="application/xml">
        <acl entries="0" version="1"/>
    </resource>
    <resource type="XMLResource" name="EHRI-ET-WL1375B310_DE_EN.xml" skip="no" owner="ehri" group="tei" mode="644" created="2024-10-15T11:28:15.882+02:00" modified="2024-10-15T11:28:15.882+02:00" filename="EHRI-ET-WL1375B310_DE_EN.xml" mimetype="application/xml">
        <acl entries="0" version="1"/>
    </resource>
    <resource type="XMLResource" name="EHRI-ET-WL1375B327_DE_EN.xml" skip="no" owner="ehri" group="tei" mode="644" created="2024-10-15T11:28:15.972+02:00" modified="2024-10-15T11:28:15.972+02:00" filename="EHRI-ET-WL1375B327_DE_EN.xml" mimetype="application/xml">
        <acl entries="0" version="1"/>
    </resource>
    <resource type="XMLResource" name="EHRI-ET-WL05320003_YI_EN.xml" skip="no" owner="ehri" group="tei" mode="644" created="2024-10-15T11:28:16.057+02:00" modified="2024-10-15T11:28:16.057+02:00" filename="EHRI-ET-WL05320003_YI_EN.xml" mimetype="application/xml">
        <acl entries="0" version="1"/>
    </resource>
    <resource type="XMLResource" name="EHRI-ET-WL05320004_YI_EN.xml" skip="no" owner="ehri" group="tei" mode="644" created="2024-10-15T11:28:16.164+02:00" modified="2024-10-15T11:28:16.164+02:00" filename="EHRI-ET-WL05320004_YI_EN.xml" mimetype="application/xml">
        <acl entries="0" version="1"/>
    </resource>
    <resource type="XMLResource" name="EHRI-ET-WL05320006_YI_EN.xml" skip="no" owner="ehri" group="tei" mode="644" created="2024-10-15T11:28:16.241+02:00" modified="2024-10-15T11:28:16.241+02:00" filename="EHRI-ET-WL05320006_YI_EN.xml" mimetype="application/xml">
        <acl entries="0" version="1"/>
    </resource>
    <resource type="XMLResource" name="EHRI-ET-WL05320010_YI_EN.xml" skip="no" owner="ehri" group="tei" mode="644" created="2024-10-15T11:28:16.299+02:00" modified="2024-10-15T11:28:16.299+02:00" filename="EHRI-ET-WL05320010_YI_EN.xml" mimetype="application/xml">
        <acl entries="0" version="1"/>
    </resource>
    <resource type="XMLResource" name="EHRI-ET-WL05320070_YI_EN.xml" skip="no" owner="ehri" group="tei" mode="644" created="2024-10-15T11:28:16.366+02:00" modified="2024-10-15T11:28:16.366+02:00" filename="EHRI-ET-WL05320070_YI_EN.xml" mimetype="application/xml">
        <acl entries="0" version="1"/>
    </resource>
    <resource type="XMLResource" name="EHRI-ET-WL05320102_YI_EN.xml" skip="no" owner="ehri" group="tei" mode="644" created="2024-10-15T11:28:16.456+02:00" modified="2024-10-15T11:28:16.456+02:00" filename="EHRI-ET-WL05320102_YI_EN.xml" mimetype="application/xml">
        <acl entries="0" version="1"/>
    </resource>
    <resource type="XMLResource" name="EHRI-ET-WL05320107_YI_EN.xml" skip="no" owner="ehri" group="tei" mode="644" created="2024-10-15T11:28:16.513+02:00" modified="2024-10-15T11:28:16.513+02:00" filename="EHRI-ET-WL05320107_YI_EN.xml" mimetype="application/xml">
        <acl entries="0" version="1"/>
    </resource>
    <resource type="XMLResource" name="EHRI-ET-WL05320114_YI_EN.xml" skip="no" owner="ehri" group="tei" mode="644" created="2024-10-15T11:28:16.647+02:00" modified="2024-10-15T11:28:16.647+02:00" filename="EHRI-ET-WL05320114_YI_EN.xml" mimetype="application/xml">
        <acl entries="0" version="1"/>
    </resource>
    <resource type="XMLResource" name="EHRI-ET-WL05320171_YI_EN.xml" skip="no" owner="ehri" group="tei" mode="644" created="2024-10-15T11:28:16.723+02:00" modified="2024-10-15T11:28:16.723+02:00" filename="EHRI-ET-WL05320171_YI_EN.xml" mimetype="application/xml">
        <acl entries="0" version="1"/>
    </resource>
    <resource type="XMLResource" name="EHRI-ET-WL05320192_YI_EN.xml" skip="no" owner="ehri" group="tei" mode="644" created="2024-10-15T11:28:16.801+02:00" modified="2024-10-15T11:28:16.801+02:00" filename="EHRI-ET-WL05320192_YI_EN.xml" mimetype="application/xml">
        <acl entries="0" version="1"/>
    </resource>
    <resource type="XMLResource" name="EHRI-ET-WL05320200_YI_EN.xml" skip="no" owner="ehri" group="tei" mode="644" created="2024-10-15T11:28:16.867+02:00" modified="2024-10-15T11:28:16.867+02:00" filename="EHRI-ET-WL05320200_YI_EN.xml" mimetype="application/xml">
        <acl entries="0" version="1"/>
    </resource>
    <resource type="XMLResource" name="EHRI-ET-WL05320220_YI_EN.xml" skip="no" owner="ehri" group="tei" mode="644" created="2024-10-15T11:28:16.974+02:00" modified="2024-10-15T11:28:16.974+02:00" filename="EHRI-ET-WL05320220_YI_EN.xml" mimetype="application/xml">
        <acl entries="0" version="1"/>
    </resource>
    <resource type="XMLResource" name="EHRI-ET-WL16560023_EN.xml" skip="no" owner="ehri" group="tei" mode="644" created="2024-10-15T11:28:17.047+02:00" modified="2024-10-15T11:28:17.047+02:00" filename="EHRI-ET-WL16560023_EN.xml" mimetype="application/xml">
        <acl entries="0" version="1"/>
    </resource>
    <resource type="XMLResource" name="EHRI-ET-WL16560044_EN.xml" skip="no" owner="ehri" group="tei" mode="644" created="2024-10-15T11:28:17.111+02:00" modified="2024-10-15T11:28:17.111+02:00" filename="EHRI-ET-WL16560044_EN.xml" mimetype="application/xml">
        <acl entries="0" version="1"/>
    </resource>
    <resource type="XMLResource" name="EHRI-ET-WL16560158_DE_EN.xml" skip="no" owner="ehri" group="tei" mode="644" created="2024-10-15T11:28:17.161+02:00" modified="2024-10-15T11:28:17.161+02:00" filename="EHRI-ET-WL16560158_DE_EN.xml" mimetype="application/xml">
        <acl entries="0" version="1"/>
    </resource>
    <resource type="XMLResource" name="EHRI-ET-WL16560176_DE_EN.xml" skip="no" owner="ehri" group="tei" mode="644" created="2024-10-15T11:28:17.322+02:00" modified="2024-10-15T11:28:17.322+02:00" filename="EHRI-ET-WL16560176_DE_EN.xml" mimetype="application/xml">
        <acl entries="0" version="1"/>
    </resource>
    <resource type="XMLResource" name="EHRI-ET-WL16560413_DE_EN.xml" skip="no" owner="ehri" group="tei" mode="644" created="2024-10-15T11:28:17.43+02:00" modified="2024-10-15T11:28:17.43+02:00" filename="EHRI-ET-WL16560413_DE_EN.xml" mimetype="application/xml">
        <acl entries="0" version="1"/>
    </resource>
    <resource type="XMLResource" name="EHRI-ET-WL16560421_DE_EN.xml" skip="no" owner="ehri" group="tei" mode="644" created="2024-10-15T11:28:17.548+02:00" modified="2024-10-15T11:28:17.547+02:00" filename="EHRI-ET-WL16560421_DE_EN.xml" mimetype="application/xml">
        <acl entries="0" version="1"/>
    </resource>
    <resource type="XMLResource" name="EHRI-ET-WL16560458_DE_EN.xml" skip="no" owner="ehri" group="tei" mode="644" created="2024-10-15T11:28:17.653+02:00" modified="2024-10-15T11:28:17.653+02:00" filename="EHRI-ET-WL16560458_DE_EN.xml" mimetype="application/xml">
        <acl entries="0" version="1"/>
    </resource>
    <resource type="XMLResource" name="EHRI-ET-WL16560540_DE_EN.xml" skip="no" owner="ehri" group="tei" mode="644" created="2024-10-15T11:28:17.753+02:00" modified="2024-10-15T11:28:17.753+02:00" filename="EHRI-ET-WL16560540_DE_EN.xml" mimetype="application/xml">
        <acl entries="0" version="1"/>
    </resource>
    <resource type="XMLResource" name="EHRI-ET-WL16560578_DE_EN.xml" skip="no" owner="ehri" group="tei" mode="644" created="2024-10-15T11:28:17.883+02:00" modified="2024-10-15T11:28:17.883+02:00" filename="EHRI-ET-WL16560578_DE_EN.xml" mimetype="application/xml">
        <acl entries="0" version="1"/>
    </resource>
    <resource type="XMLResource" name="EHRI-ET-WL16560633_FR_EN.xml" skip="no" owner="ehri" group="tei" mode="644" created="2024-10-15T11:28:17.962+02:00" modified="2024-10-15T11:28:17.962+02:00" filename="EHRI-ET-WL16560633_FR_EN.xml" mimetype="application/xml">
        <acl entries="0" version="1"/>
    </resource>
    <resource type="XMLResource" name="EHRI-ET-WL16560707_DE_EN.xml" skip="no" owner="ehri" group="tei" mode="644" created="2024-10-15T11:28:18.027+02:00" modified="2024-10-15T11:28:18.027+02:00" filename="EHRI-ET-WL16560707_DE_EN.xml" mimetype="application/xml">
        <acl entries="0" version="1"/>
    </resource>
    <resource type="XMLResource" name="EHRI-ET-WL16560771_DE_EN.xml" skip="no" owner="ehri" group="tei" mode="644" created="2024-10-15T11:28:18.126+02:00" modified="2024-10-15T11:28:18.126+02:00" filename="EHRI-ET-WL16560771_DE_EN.xml" mimetype="application/xml">
        <acl entries="0" version="1"/>
    </resource>
    <resource type="XMLResource" name="EHRI-ET-WL16560866_DE_EN.xml" skip="no" owner="ehri" group="tei" mode="644" created="2024-10-15T11:28:18.221+02:00" modified="2024-10-15T11:28:18.221+02:00" filename="EHRI-ET-WL16560866_DE_EN.xml" mimetype="application/xml">
        <acl entries="0" version="1"/>
    </resource>
    <resource type="XMLResource" name="EHRI-ET-WL16560939_DE_EN.xml" skip="no" owner="ehri" group="tei" mode="644" created="2024-10-15T11:28:18.295+02:00" modified="2024-10-15T11:28:18.295+02:00" filename="EHRI-ET-WL16560939_DE_EN.xml" mimetype="application/xml">
        <acl entries="0" version="1"/>
    </resource>
    <resource type="XMLResource" name="EHRI-ET-WL16560946_DE_EN.xml" skip="no" owner="ehri" group="tei" mode="644" created="2024-10-15T11:28:18.37+02:00" modified="2024-10-15T11:28:18.37+02:00" filename="EHRI-ET-WL16560946_DE_EN.xml" mimetype="application/xml">
        <acl entries="0" version="1"/>
    </resource>
    <resource type="XMLResource" name="EHRI-ET-WL16560956_DE_EN.xml" skip="no" owner="ehri" group="tei" mode="644" created="2024-10-15T11:28:18.432+02:00" modified="2024-10-15T11:28:18.432+02:00" filename="EHRI-ET-WL16560956_DE_EN.xml" mimetype="application/xml">
        <acl entries="0" version="1"/>
    </resource>
    <resource type="XMLResource" name="EHRI-ET-YV3540315_YI_EN.xml" skip="no" owner="ehri" group="tei" mode="644" created="2024-10-15T11:28:18.507+02:00" modified="2024-10-15T11:28:18.507+02:00" filename="EHRI-ET-YV3540315_YI_EN.xml" mimetype="application/xml">
        <acl entries="0" version="1"/>
    </resource>
    <resource type="XMLResource" name="EHRI-ET-YV3540317_YI_EN.xml" skip="no" owner="ehri" group="tei" mode="644" created="2024-10-15T11:28:18.579+02:00" modified="2024-10-15T11:28:18.579+02:00" filename="EHRI-ET-YV3540317_YI_EN.xml" mimetype="application/xml">
        <acl entries="0" version="1"/>
    </resource>
    <resource type="XMLResource" name="EHRI-ET-YV3540320_YI_EN.xml" skip="no" owner="ehri" group="tei" mode="644" created="2024-10-15T11:28:18.644+02:00" modified="2024-10-15T11:28:18.644+02:00" filename="EHRI-ET-YV3540320_YI_EN.xml" mimetype="application/xml">
        <acl entries="0" version="1"/>
    </resource>
    <resource type="XMLResource" name="EHRI-ET-YV3540377_YI_EN.xml" skip="no" owner="ehri" group="tei" mode="644" created="2024-10-15T11:28:18.698+02:00" modified="2024-10-15T11:28:18.698+02:00" filename="EHRI-ET-YV3540377_YI_EN.xml" mimetype="application/xml">
        <acl entries="0" version="1"/>
    </resource>
    <resource type="XMLResource" name="EHRI-ET-YV3540424_YI_EN.xml" skip="no" owner="ehri" group="tei" mode="644" created="2024-10-15T11:28:18.745+02:00" modified="2024-10-15T11:28:18.745+02:00" filename="EHRI-ET-YV3540424_YI_EN.xml" mimetype="application/xml">
        <acl entries="0" version="1"/>
    </resource>
    <resource type="XMLResource" name="EHRI-ET-YV3540469_YI_EN.xml" skip="no" owner="ehri" group="tei" mode="644" created="2024-10-15T11:28:18.789+02:00" modified="2024-10-15T11:28:18.789+02:00" filename="EHRI-ET-YV3540469_YI_EN.xml" mimetype="application/xml">
        <acl entries="0" version="1"/>
    </resource>
    <resource type="XMLResource" name="EHRI-ET-YV3540549_YI_EN.xml" skip="no" owner="ehri" group="tei" mode="644" created="2024-10-15T11:28:18.846+02:00" modified="2024-10-15T11:28:18.846+02:00" filename="EHRI-ET-YV3540549_YI_EN.xml" mimetype="application/xml">
        <acl entries="0" version="1"/>
    </resource>
    <resource type="XMLResource" name="EHRI-ET-YV3540561_YI_EN.xml" skip="no" owner="ehri" group="tei" mode="644" created="2024-10-15T11:28:18.912+02:00" modified="2024-10-15T11:28:18.912+02:00" filename="EHRI-ET-YV3540561_YI_EN.xml" mimetype="application/xml">
        <acl entries="0" version="1"/>
    </resource>
    <resource type="XMLResource" name="EHRI-ET-YV3540579_YI_EN.xml" skip="no" owner="ehri" group="tei" mode="644" created="2024-10-15T11:28:18.964+02:00" modified="2024-10-15T11:28:18.964+02:00" filename="EHRI-ET-YV3540579_YI_EN.xml" mimetype="application/xml">
        <acl entries="0" version="1"/>
    </resource>
    <resource type="XMLResource" name="EHRI-ET-YV3540604_YI_EN.xml" skip="no" owner="ehri" group="tei" mode="644" created="2024-10-15T11:28:19.037+02:00" modified="2024-10-15T11:28:19.037+02:00" filename="EHRI-ET-YV3540604_YI_EN.xml" mimetype="application/xml">
        <acl entries="0" version="1"/>
    </resource>
    <resource type="XMLResource" name="EHRI-ET-YV3540639_YI_EN.xml" skip="no" owner="ehri" group="tei" mode="644" created="2024-10-15T11:28:19.095+02:00" modified="2024-10-15T11:28:19.095+02:00" filename="EHRI-ET-YV3540639_YI_EN.xml" mimetype="application/xml">
        <acl entries="0" version="1"/>
    </resource>
    <resource type="XMLResource" name="EHRI-ET-YV3549213_DE_EN.xml" skip="no" owner="ehri" group="tei" mode="644" created="2024-10-15T11:28:19.161+02:00" modified="2024-10-15T11:28:19.161+02:00" filename="EHRI-ET-YV3549213_DE_EN.xml" mimetype="application/xml">
        <acl entries="0" version="1"/>
    </resource>
    <resource type="XMLResource" name="EHRI-ET-YV3549219_DE_EN.xml" skip="no" owner="ehri" group="tei" mode="644" created="2024-10-15T11:28:19.242+02:00" modified="2024-10-15T11:28:19.242+02:00" filename="EHRI-ET-YV3549219_DE_EN.xml" mimetype="application/xml">
        <acl entries="0" version="1"/>
    </resource>
    <resource type="XMLResource" name="EHRI-ET-YV3549264_EN.xml" skip="no" owner="ehri" group="tei" mode="644" created="2024-10-15T11:28:19.363+02:00" modified="2024-10-15T11:28:19.363+02:00" filename="EHRI-ET-YV3549264_EN.xml" mimetype="application/xml">
        <acl entries="0" version="1"/>
    </resource>
    <resource type="XMLResource" name="EHRI-ET-YV3549466_DE_EN.xml" skip="no" owner="ehri" group="tei" mode="644" created="2024-10-15T11:28:19.452+02:00" modified="2024-10-15T11:28:19.452+02:00" filename="EHRI-ET-YV3549466_DE_EN.xml" mimetype="application/xml">
        <acl entries="0" version="1"/>
    </resource>
    <resource type="XMLResource" name="EHRI-ET-YV3552513_YI_EN.xml" skip="no" owner="ehri" group="tei" mode="644" created="2024-10-15T11:28:19.563+02:00" modified="2024-10-15T11:28:19.563+02:00" filename="EHRI-ET-YV3552513_YI_EN.xml" mimetype="application/xml">
        <acl entries="0" version="1"/>
    </resource>
    <resource type="XMLResource" name="EHRI-ET-YV4693907_EN.xml" skip="no" owner="ehri" group="tei" mode="644" created="2024-10-15T11:28:19.71+02:00" modified="2024-10-15T11:28:19.71+02:00" filename="EHRI-ET-YV4693907_EN.xml" mimetype="application/xml">
        <acl entries="0" version="1"/>
    </resource>
    <resource type="XMLResource" name="EHRI-ET-DEGOB0090_HU_EN.xml" skip="no" owner="ehri" group="tei" mode="644" created="2024-10-15T11:28:12.43+02:00" modified="2024-10-15T11:28:12.43+02:00" filename="EHRI-ET-DEGOB0090_HU_EN.xml" mimetype="application/xml">
        <acl entries="0" version="1"/>
    </resource>
    <resource type="XMLResource" name="EHRI-ET-YV5082493_EN.xml" skip="no" owner="ehri" group="tei" mode="644" created="2024-10-15T11:28:19.76+02:00" modified="2024-10-15T11:28:19.76+02:00" filename="EHRI-ET-YV5082493_EN.xml" mimetype="application/xml">
        <acl entries="0" version="1"/>
    </resource>
    <resource type="XMLResource" name="EHRI-ET-DEGOB0086_HU_EN.xml" skip="no" owner="ehri" group="tei" mode="644" created="2024-10-15T11:28:12.352+02:00" modified="2024-10-15T11:28:12.352+02:00" filename="EHRI-ET-DEGOB0086_HU_EN.xml" mimetype="application/xml">
        <acl entries="0" version="1"/>
    </resource>
    <resource type="XMLResource" name="EHRI-ET-YV5245989_DE_EN.xml" skip="no" owner="ehri" group="tei" mode="644" created="2024-10-15T11:28:19.803+02:00" modified="2024-10-15T11:28:19.803+02:00" filename="EHRI-ET-YV5245989_DE_EN.xml" mimetype="application/xml">
        <acl entries="0" version="1"/>
    </resource>
    <resource type="XMLResource" name="EHRI-ET-DEGOB0005_HU_EN.xml" skip="no" owner="ehri" group="tei" mode="644" created="2024-10-15T11:28:12.168+02:00" modified="2024-10-15T11:28:12.168+02:00" filename="EHRI-ET-DEGOB0005_HU_EN.xml" mimetype="application/xml">
        <acl entries="0" version="1"/>
    </resource>
    <resource type="XMLResource" name="EHRI-ET-YV9392546_EN.xml" skip="no" owner="ehri" group="tei" mode="644" created="2024-10-15T11:28:19.885+02:00" modified="2024-10-15T11:28:19.885+02:00" filename="EHRI-ET-YV9392546_EN.xml" mimetype="application/xml">
        <acl entries="0" version="1"/>
    </resource>
    <resource type="XMLResource" name="EHRI-ET-ZIH3010002_PL_EN.xml" skip="no" owner="ehri" group="tei" mode="644" created="2024-10-15T11:28:19.942+02:00" modified="2024-10-15T11:28:19.942+02:00" filename="EHRI-ET-ZIH3010002_PL_EN.xml" mimetype="application/xml">
        <acl entries="0" version="1"/>
    </resource>
    <resource type="XMLResource" name="EHRI-ET-ZIH3010005_YI_EN.xml" skip="no" owner="ehri" group="tei" mode="644" created="2024-10-15T11:28:19.99+02:00" modified="2024-10-15T11:28:19.99+02:00" filename="EHRI-ET-ZIH3010005_YI_EN.xml" mimetype="application/xml">
        <acl entries="0" version="1"/>
    </resource>
    <resource type="XMLResource" name="EHRI-ET-ZIH3010012_PL_EN.xml" skip="no" owner="ehri" group="tei" mode="644" created="2024-10-15T11:28:20.047+02:00" modified="2024-10-15T11:28:20.047+02:00" filename="EHRI-ET-ZIH3010012_PL_EN.xml" mimetype="application/xml">
        <acl entries="0" version="1"/>
    </resource>
    <resource type="XMLResource" name="EHRI-ET-ZIH3010014_PL_EN.xml" skip="no" owner="ehri" group="tei" mode="644" created="2024-10-15T11:28:20.092+02:00" modified="2024-10-15T11:28:20.092+02:00" filename="EHRI-ET-ZIH3010014_PL_EN.xml" mimetype="application/xml">
        <acl entries="0" version="1"/>
    </resource>
    <resource type="XMLResource" name="EHRI-ET-ZIH3010025_YI_EN.xml" skip="no" owner="ehri" group="tei" mode="644" created="2024-10-15T11:28:20.16+02:00" modified="2024-10-15T11:28:20.16+02:00" filename="EHRI-ET-ZIH3010025_YI_EN.xml" mimetype="application/xml">
        <acl entries="0" version="1"/>
    </resource>
    <resource type="XMLResource" name="EHRI-ET-ZIH3010036_YI_EN.xml" skip="no" owner="ehri" group="tei" mode="644" created="2024-10-15T11:28:20.241+02:00" modified="2024-10-15T11:28:20.241+02:00" filename="EHRI-ET-ZIH3010036_YI_EN.xml" mimetype="application/xml">
        <acl entries="0" version="1"/>
    </resource>
    <resource type="XMLResource" name="EHRI-ET-ZIH3010081_PL_EN.xml" skip="no" owner="ehri" group="tei" mode="644" created="2024-10-15T11:28:20.326+02:00" modified="2024-10-15T11:28:20.326+02:00" filename="EHRI-ET-ZIH3010081_PL_EN.xml" mimetype="application/xml">
        <acl entries="0" version="1"/>
    </resource>
    <resource type="XMLResource" name="EHRI-ET-ZIH3010106_PL_EN.xml" skip="no" owner="ehri" group="tei" mode="644" created="2024-10-15T11:28:20.386+02:00" modified="2024-10-15T11:28:20.386+02:00" filename="EHRI-ET-ZIH3010106_PL_EN.xml" mimetype="application/xml">
        <acl entries="0" version="1"/>
    </resource>
    <resource type="XMLResource" name="EHRI-ET-ZIH3010107_YI_EN.xml" skip="no" owner="ehri" group="tei" mode="644" created="2024-10-15T11:28:20.445+02:00" modified="2024-10-15T11:28:20.444+02:00" filename="EHRI-ET-ZIH3010107_YI_EN.xml" mimetype="application/xml">
        <acl entries="0" version="1"/>
    </resource>
    <resource type="XMLResource" name="EHRI-ET-ZIH3010191_PL_EN.xml" skip="no" owner="ehri" group="tei" mode="644" created="2024-10-15T11:28:20.509+02:00" modified="2024-10-15T11:28:20.508+02:00" filename="EHRI-ET-ZIH3010191_PL_EN.xml" mimetype="application/xml">
        <acl entries="0" version="1"/>
    </resource>
    <resource type="XMLResource" name="EHRI-ET-ZIH3010201_PL_EN.xml" skip="no" owner="ehri" group="tei" mode="644" created="2024-10-15T11:28:20.566+02:00" modified="2024-10-15T11:28:20.566+02:00" filename="EHRI-ET-ZIH3010201_PL_EN.xml" mimetype="application/xml">
        <acl entries="0" version="1"/>
    </resource>
    <resource type="XMLResource" name="EHRI-ET-ZIH3010203_PL_EN.xml" skip="no" owner="ehri" group="tei" mode="644" created="2024-10-15T11:28:20.611+02:00" modified="2024-10-15T11:28:20.611+02:00" filename="EHRI-ET-ZIH3010203_PL_EN.xml" mimetype="application/xml">
        <acl entries="0" version="1"/>
    </resource>
    <resource type="XMLResource" name="EHRI-ET-ZIH3010317_YI_EN.xml" skip="no" owner="ehri" group="tei" mode="644" created="2024-10-15T11:28:20.662+02:00" modified="2024-10-15T11:28:20.662+02:00" filename="EHRI-ET-ZIH3010317_YI_EN.xml" mimetype="application/xml">
        <acl entries="0" version="1"/>
    </resource>
    <resource type="XMLResource" name="EHRI-ET-ZIH3010481_PL_EN.xml" skip="no" owner="ehri" group="tei" mode="644" created="2024-10-15T11:28:20.722+02:00" modified="2024-10-15T11:28:20.721+02:00" filename="EHRI-ET-ZIH3010481_PL_EN.xml" mimetype="application/xml">
        <acl entries="0" version="1"/>
    </resource>
    <resource type="XMLResource" name="EHRI-ET-ZIH3010545_YI_EN.xml" skip="no" owner="ehri" group="tei" mode="644" created="2024-10-15T11:28:20.772+02:00" modified="2024-10-15T11:28:20.772+02:00" filename="EHRI-ET-ZIH3010545_YI_EN.xml" mimetype="application/xml">
        <acl entries="0" version="1"/>
    </resource>
    <resource type="XMLResource" name="EHRI-ET-ZIH3010805_PL_EN.xml" skip="no" owner="ehri" group="tei" mode="644" created="2024-10-15T11:28:20.819+02:00" modified="2024-10-15T11:28:20.819+02:00" filename="EHRI-ET-ZIH3010805_PL_EN.xml" mimetype="application/xml">
        <acl entries="0" version="1"/>
    </resource>
    <resource type="XMLResource" name="EHRI-ET-ZIH3010884_PL_EN.xml" skip="no" owner="ehri" group="tei" mode="644" created="2024-10-15T11:28:20.883+02:00" modified="2024-10-15T11:28:20.883+02:00" filename="EHRI-ET-ZIH3010884_PL_EN.xml" mimetype="application/xml">
        <acl entries="0" version="1"/>
    </resource>
    <resource type="XMLResource" name="EHRI-ET-ZIH3010905_PL_EN.xml" skip="no" owner="ehri" group="tei" mode="644" created="2024-10-15T11:28:20.952+02:00" modified="2024-10-15T11:28:20.952+02:00" filename="EHRI-ET-ZIH3010905_PL_EN.xml" mimetype="application/xml">
        <acl entries="0" version="1"/>
    </resource>
    <resource type="XMLResource" name="EHRI-ET-ZIH3010945_PL_EN.xml" skip="no" owner="ehri" group="tei" mode="644" created="2024-10-15T11:28:20.996+02:00" modified="2024-10-15T11:28:20.996+02:00" filename="EHRI-ET-ZIH3010945_PL_EN.xml" mimetype="application/xml">
        <acl entries="0" version="1"/>
    </resource>
    <resource type="XMLResource" name="EHRI-ET-ZIH3010965_PL_EN.xml" skip="no" owner="ehri" group="tei" mode="644" created="2024-10-15T11:28:21.061+02:00" modified="2024-10-15T11:28:21.061+02:00" filename="EHRI-ET-ZIH3010965_PL_EN.xml" mimetype="application/xml">
        <acl entries="0" version="1"/>
    </resource>
    <resource type="XMLResource" name="EHRI-ET-ZIH3011116_PL_EN.xml" skip="no" owner="ehri" group="tei" mode="644" created="2024-10-15T11:28:21.109+02:00" modified="2024-10-15T11:28:21.109+02:00" filename="EHRI-ET-ZIH3011116_PL_EN.xml" mimetype="application/xml">
        <acl entries="0" version="1"/>
    </resource>
    <resource type="XMLResource" name="EHRI-ET-ZIH3011129_PL_EN.xml" skip="no" owner="ehri" group="tei" mode="644" created="2024-10-15T11:28:21.163+02:00" modified="2024-10-15T11:28:21.163+02:00" filename="EHRI-ET-ZIH3011129_PL_EN.xml" mimetype="application/xml">
        <acl entries="0" version="1"/>
    </resource>
    <resource type="XMLResource" name="EHRI-ET-ZIH3011169_PL_EN.xml" skip="no" owner="ehri" group="tei" mode="644" created="2024-10-15T11:28:21.214+02:00" modified="2024-10-15T11:28:21.214+02:00" filename="EHRI-ET-ZIH3011169_PL_EN.xml" mimetype="application/xml">
        <acl entries="0" version="1"/>
    </resource>
    <resource type="XMLResource" name="EHRI-ET-ZIH3011538_PL_EN.xml" skip="no" owner="ehri" group="tei" mode="644" created="2024-10-15T11:28:21.271+02:00" modified="2024-10-15T11:28:21.271+02:00" filename="EHRI-ET-ZIH3011538_PL_EN.xml" mimetype="application/xml">
        <acl entries="0" version="1"/>
    </resource>
    <resource type="XMLResource" name="EHRI-ET-ZIH3011649_PL_EN.xml" skip="no" owner="ehri" group="tei" mode="644" created="2024-10-15T11:28:21.328+02:00" modified="2024-10-15T11:28:21.328+02:00" filename="EHRI-ET-ZIH3011649_PL_EN.xml" mimetype="application/xml">
        <acl entries="0" version="1"/>
    </resource>
    <resource type="XMLResource" name="EHRI-ET-ZIH3011713_PL_EN.xml" skip="no" owner="ehri" group="tei" mode="644" created="2024-10-15T11:28:21.389+02:00" modified="2024-10-15T11:28:21.389+02:00" filename="EHRI-ET-ZIH3011713_PL_EN.xml" mimetype="application/xml">
        <acl entries="0" version="1"/>
    </resource>
    <resource type="XMLResource" name="EHRI-ET-DEGOB0651_HU_EN.xml" skip="no" owner="ehri" group="tei" mode="644" created="2024-10-15T11:28:12.626+02:00" modified="2024-10-15T11:28:12.626+02:00" filename="EHRI-ET-DEGOB0651_HU_EN.xml" mimetype="application/xml">
        <acl entries="0" version="1"/>
    </resource>
    <resource type="XMLResource" name="EHRI-ET-DEGOB0594_HU_EN.xml" skip="no" owner="ehri" group="tei" mode="644" created="2024-10-15T11:28:12.565+02:00" modified="2024-10-15T11:28:12.565+02:00" filename="EHRI-ET-DEGOB0594_HU_EN.xml" mimetype="application/xml">
        <acl entries="0" version="1"/>
    </resource>
    <resource type="XMLResource" name="EHRI-ET-DEGOB0099_HU_EN.xml" skip="no" owner="ehri" group="tei" mode="644" created="2024-10-15T11:28:12.507+02:00" modified="2024-10-15T11:28:12.507+02:00" filename="EHRI-ET-DEGOB0099_HU_EN.xml" mimetype="application/xml">
        <acl entries="0" version="1"/>
    </resource>
</collection>