<collection xmlns="http://exist.sourceforge.net/NS/exist" name="/db/apps/ehri-online-editions/resources/i18n/app" version="1" owner="ehri" group="tei" mode="755" created="2023-07-31T15:39:01.014+02:00">
    <acl entries="0" version="1"/>
    <resource type="BinaryResource" name="fr.json" skip="no" owner="ehri" group="tei" mode="644" created="2023-08-02T15:20:36.889+02:00" modified="2023-08-02T15:32:19.657+02:00" filename="fr.json" mimetype="application/json">
        <acl entries="0" version="1"/>
    </resource>
    <resource type="BinaryResource" name="en.json" skip="no" owner="ehri" group="tei" mode="644" created="2023-07-31T15:39:01.016+02:00" modified="2023-08-02T15:33:22.429+02:00" filename="en.json" mimetype="application/json">
        <acl entries="0" version="1"/>
    </resource>
    <resource type="BinaryResource" name="de.json" skip="no" owner="ehri" group="tei" mode="644" created="2023-08-02T15:20:45.421+02:00" modified="2023-08-02T15:33:32.152+02:00" filename="de.json" mimetype="application/json">
        <acl entries="0" version="1"/>
    </resource>
</collection>